poe_cli/__init__.py
poe_cli/main.py
poe_cli-0.1.1.dist-info/LICENSE
poe_cli-0.1.1.dist-info/METADATA
poe_cli-0.1.1.dist-info/WHEEL
poe_cli-0.1.1.dist-info/entry_points.txt
poe_cli-0.1.1.dist-info/top_level.txt
poe_cli-0.1.1.dist-info/RECORD
